{
    "tableName": "setting",
    "dumpFile": "dump\/setting.sql",
    "index": [
        {
            "column_name": "Id",
            "key_name": "PRIMARY",
            "non_uniqe": "0"
        }
    ],
    "colums": [
        {
            "COLUMN_NAME": "Id",
            "COLUMN_TYPE": "varchar(35)",
            "CHARACTER_SET_NAME": "latin1",
            "COLLATION_NAME": "latin1_general_ci",
            "IS_NULLABLE": "NO"
        },
        {
            "COLUMN_NAME": "nilai",
            "COLUMN_TYPE": "varchar(255)",
            "CHARACTER_SET_NAME": "latin1",
            "COLLATION_NAME": "latin1_general_ci",
            "IS_NULLABLE": "YES"
        },
        {
            "COLUMN_NAME": "ket",
            "COLUMN_TYPE": "varchar(255)",
            "CHARACTER_SET_NAME": "latin1",
            "COLLATION_NAME": "latin1_general_ci",
            "IS_NULLABLE": "YES"
        },
        {
            "COLUMN_NAME": "grup",
            "COLUMN_TYPE": "varchar(255)",
            "CHARACTER_SET_NAME": "latin1",
            "COLLATION_NAME": "latin1_general_ci",
            "IS_NULLABLE": "YES"
        },
        {
            "COLUMN_NAME": "tgl_update",
            "COLUMN_TYPE": "datetime",
            "CHARACTER_SET_NAME": null,
            "COLLATION_NAME": null,
            "IS_NULLABLE": "YES"
        },
        {
            "COLUMN_NAME": "uid",
            "COLUMN_TYPE": "varchar(20)",
            "CHARACTER_SET_NAME": "latin1",
            "COLLATION_NAME": "latin1_general_ci",
            "IS_NULLABLE": "YES"
        },
        {
            "COLUMN_NAME": "label",
            "COLUMN_TYPE": "varchar(255)",
            "CHARACTER_SET_NAME": "latin1",
            "COLLATION_NAME": "latin1_general_ci",
            "IS_NULLABLE": "YES"
        },
        {
            "COLUMN_NAME": "urut",
            "COLUMN_TYPE": "int(11)",
            "CHARACTER_SET_NAME": null,
            "COLLATION_NAME": null,
            "IS_NULLABLE": "YES"
        },
        {
            "COLUMN_NAME": "status",
            "COLUMN_TYPE": "tinyint(3)",
            "CHARACTER_SET_NAME": null,
            "COLLATION_NAME": null,
            "IS_NULLABLE": "YES"
        }
    ],
    "default_value": [
        "INSERT INTO setting (Id,nilai,ket,grup,tgl_update,uid,label,urut,status) values ('akun_pemanfaat','','','','','','','','0') ",
        "INSERT INTO setting (Id,nilai,ket,grup,tgl_update,uid,label,urut,status) values ('CEK_BI','1','cek bi di penatausahaan, penysuutan','','','','','','0') ",
        "INSERT INTO setting (Id,nilai,ket,grup,tgl_update,uid,label,urut,status) values ('CEK_BI_REKAP','0','cek bi di kertas kerja','','','','','','0') ",
        "INSERT INTO setting (Id,nilai,ket,grup,tgl_update,uid,label,urut,status) values ('CEK_MAPPING_BELANJA_MODAL','0','CEK MAPPING BELANJA MODAL','PERENCANAAN','2018-07-02 00:00:00','kszxpo','CEK MAPPING BELANJA MODAL','','1') ",
        "INSERT INTO setting (Id,nilai,ket,grup,tgl_update,uid,label,urut,status) values ('CEK_PAGU_INDIKATIF','0','CEK PAGU INDIKATIF','PERENCANAAN','2018-07-02 00:00:00','kszxpo','PAGU INDIKATIF RKA','','1') ",
        "INSERT INTO setting (Id,nilai,ket,grup,tgl_update,uid,label,urut,status) values ('CEK_PLAFON_ANGGARAN','1','CEK_PLAFON_ANGGARAN','PERENCANAAN','2018-07-02 00:00:00','kszxpo','CEK_PLAFON_ANGGARAN','','1') ",
        "INSERT INTO setting (Id,nilai,ket,grup,tgl_update,uid,label,urut,status) values ('CETAK_TIDAK_TAMPIL_SKPD','0','cetak penatausaahaan tidak tampil skpd di kolom ket','','','','','','0') ",
        "INSERT INTO setting (Id,nilai,ket,grup,tgl_update,uid,label,urut,status) values ('DEF_KEPEMILIKAN','12','12 . milik kota, 11 milik prov','PEMDA','','','Kode Kepemilikan','3','1') ",
        "INSERT INTO setting (Id,nilai,ket,grup,tgl_update,uid,label,urut,status) values ('DEF_PROPINSI','28','kode prov','PEMDA','','','Kode Propinsi','5','1') ",
        "INSERT INTO setting (Id,nilai,ket,grup,tgl_update,uid,label,urut,status) values ('DEF_WILAYAH','03','kode kota\/kab','PEMDA','','','Kode Kab\/Kota','6','1') ",
        "INSERT INTO setting (Id,nilai,ket,grup,tgl_update,uid,label,urut,status) values ('KD_AKUMSUSUT','1.3.7','','','','','','','0') ",
        "INSERT INTO setting (Id,nilai,ket,grup,tgl_update,uid,label,urut,status) values ('KD_ASET_LAINLAIN','1.5.4.1','','','','','','','0') ",
        "INSERT INTO setting (Id,nilai,ket,grup,tgl_update,uid,label,urut,status) values ('KD_ASET_TETAP','1.3','','','','','','','0') ",
        "INSERT INTO setting (Id,nilai,ket,grup,tgl_update,uid,label,urut,status) values ('KD_BELANJA','5','','','','','','','0') ",
        "INSERT INTO setting (Id,nilai,ket,grup,tgl_update,uid,label,urut,status) values ('KD_BELANJA_BRGJASA','5.1.2','','','','','','','0') ",
        "INSERT INTO setting (Id,nilai,ket,grup,tgl_update,uid,label,urut,status) values ('KD_BELANJA_MODAL','5.2','kd akun','','','','','','0') ",
        "INSERT INTO setting (Id,nilai,ket,grup,tgl_update,uid,label,urut,status) values ('KD_PENDAPATAN_HIBAH','4.3.1','','','','','','','0') ",
        "INSERT INTO setting (Id,nilai,ket,grup,tgl_update,uid,label,urut,status) values ('LOCK_JUMLAH_OPTIMAL','0','1=LOCK 0 = UNLOCK','MODUL','','kszxpo','MODUL PERENCANAAN','','0') ",
        "INSERT INTO setting (Id,nilai,ket,grup,tgl_update,uid,label,urut,status) values ('MAP_CENTER_POINT','-6.115333 106.152317','set berdasar pemda, center google map, pemisah spasi','PETA','','','','','0') ",
        "INSERT INTO setting (Id,nilai,ket,grup,tgl_update,uid,label,urut,status) values ('MAP_ZOOM','11','set map zoom awal','PETA','','','','','0') ",
        "INSERT INTO setting (Id,nilai,ket,grup,tgl_update,uid,label,urut,status) values ('MENU_VERSI','3','0=defaulkt, 1 pp27, 2= mantap kota bandung 3=permen19, 4= peta sebaran subang, 5 menu baru','MENU','','','','','0') ",
        "INSERT INTO setting (Id,nilai,ket,grup,tgl_update,uid,label,urut,status) values ('MODE_MAINTENANCE','0','1=disable autoclosing thn awal','','','','','','0') ",
        "INSERT INTO setting (Id,nilai,ket,grup,tgl_update,uid,label,urut,status) values ('MODUL_GANTIRUGI','1','','MODUL','','','Modul Ganti Rugi','','0') ",
        "INSERT INTO setting (Id,nilai,ket,grup,tgl_update,uid,label,urut,status) values ('MODUL_MUTASI','1','','MODUL','','','Modul Mutasi SKPD','','0') ",
        "INSERT INTO setting (Id,nilai,ket,grup,tgl_update,uid,label,urut,status) values ('MODUL_PEMANFAATAN','1','','MODUL','','','Modul Pemanfaatan','','0') ",
        "INSERT INTO setting (Id,nilai,ket,grup,tgl_update,uid,label,urut,status) values ('MODUL_PEMELIHARAAN','1','1. Modul aktif,, 0 . tidak','MODUL','','','Modul Pemeliharaan','','0') ",
        "INSERT INTO setting (Id,nilai,ket,grup,tgl_update,uid,label,urut,status) values ('MODUL_PEMINDAHTANGAN','1','','','','','Modul Pemindahtanganan','','0') ",
        "INSERT INTO setting (Id,nilai,ket,grup,tgl_update,uid,label,urut,status) values ('MODUL_PENGAMANAN','1','','MODUL','','','Modul Pengamanan','','0') ",
        "INSERT INTO setting (Id,nilai,ket,grup,tgl_update,uid,label,urut,status) values ('MODUL_PETA','1','','','','','Modul Peta','','0') ",
        "INSERT INTO setting (Id,nilai,ket,grup,tgl_update,uid,label,urut,status) values ('NM_KEPEMILIKAN','Pemerintah Kabupaten\/Kota','','PEMDA','','','Nama Kepemilikan','4','1') ",
        "INSERT INTO setting (Id,nilai,ket,grup,tgl_update,uid,label,urut,status) values ('NM_WILAYAH','Kabupaten Pandeglang','','PEMDA','','','Nama Pemda','7','1') ",
        "INSERT INTO setting (Id,nilai,ket,grup,tgl_update,uid,label,urut,status) values ('NM_WILAYAH2','PEMERINTAH KABUPATEN PANDEGLANG','','PEMDA','','','Nama Pemda 2','8','1') ",
        "INSERT INTO setting (Id,nilai,ket,grup,tgl_update,uid,label,urut,status) values ('PENERIMAAN_P19','1','modul penermaan p19 1=aktif, 0=tidak aktif','','','','','','0') ",
        "INSERT INTO setting (Id,nilai,ket,grup,tgl_update,uid,label,urut,status) values ('PERENCANAAN_PERSEDIAAN','1','1 = SHOW 0 = HIDDEN','MODUL','','kszxpo','PERENCANAAN','','0') ",
        "INSERT INTO setting (Id,nilai,ket,grup,tgl_update,uid,label,urut,status) values ('POST_REKAP_STEP','30','step untuk progress posting ke jurnal rekap','REKAP','','','','','0') ",
        "INSERT INTO setting (Id,nilai,ket,grup,tgl_update,uid,label,urut,status) values ('SENSUS_VERSI','2','menggunakan pengaturan tahun sensus','SENSUS','','','','','0') ",
        "INSERT INTO setting (Id,nilai,ket,grup,tgl_update,uid,label,urut,status) values ('SIST_ASET','1','1= aktif , 0 tidak','','','','','','0') ",
        "INSERT INTO setting (Id,nilai,ket,grup,tgl_update,uid,label,urut,status) values ('SIST_PERSEDIAAN','1','1= aktif , 0 tidak','','','','','','0') ",
        "INSERT INTO setting (Id,nilai,ket,grup,tgl_update,uid,label,urut,status) values ('SUSUT_MODE','7','mode penyusutan','','','','','','0') ",
        "INSERT INTO setting (Id,nilai,ket,grup,tgl_update,uid,label,urut,status) values ('THN_ANGGARAN','2017','tahun anggaran \/ thn login','','','','','','0') ",
        "INSERT INTO setting (Id,nilai,ket,grup,tgl_update,uid,label,urut,status) values ('THN_INVENTARIS','','Tahun  inventaris  yg aktif','INVENTARIS','','','','','0') ",
        "INSERT INTO setting (Id,nilai,ket,grup,tgl_update,uid,label,urut,status) values ('THN_MULAI_SUSUT','0','TAHUN_MULAI_SUSUT','','','','','','0') ",
        "INSERT INTO setting (Id,nilai,ket,grup,tgl_update,uid,label,urut,status) values ('THN_SENSUS','2016','Tahun  sensus yg aktif','SENSUS','','','','','0') ",
        "INSERT INTO setting (Id,nilai,ket,grup,tgl_update,uid,label,urut,status) values ('URUSAN','1','seting skpd  0=tanpa, 1=dengan urusan','','','','','','0') ",
        "INSERT INTO setting (Id,nilai,ket,grup,tgl_update,uid,label,urut,status) values ('VERSI_NAME','PANDEGLANG','','','','','Versi Name','2','1') "
    ]
}
